pyflexad/__init__.py
pyflexad/math/__init__.py
pyflexad/math/iabvg.py
pyflexad/math/iabvg_jit.py
pyflexad/math/lpvg.py
pyflexad/math/lpvg_gurobipy.py
pyflexad/math/lpvg_pyomo.py
pyflexad/math/polytope.py
pyflexad/math/signal_vectors.py
pyflexad/models/__init__.py
pyflexad/models/bess/__init__.py
pyflexad/models/bess/generac.py
pyflexad/models/bess/tesla.py
pyflexad/models/ev/__init__.py
pyflexad/models/ev/nissan.py
pyflexad/models/ev/renault.py
pyflexad/models/ev/tesla.py
pyflexad/models/tclc/__init__.py
pyflexad/models/tclc/generic.py
pyflexad/models/tclh/__init__.py
pyflexad/models/tclh/generic.py
pyflexad/optimization/__init__.py
pyflexad/optimization/centralized_controller.py
pyflexad/optimization/centralized_cost_controller.py
pyflexad/optimization/centralized_power_controller.py
pyflexad/optimization/vertex_based_controller.py
pyflexad/optimization/vertex_based_cost_controller.py
pyflexad/optimization/vertex_based_power_controller.py
pyflexad/parameters/__init__.py
pyflexad/parameters/general_parameters.py
pyflexad/parameters/hardware_parameters.py
pyflexad/parameters/usage_parameters.py
pyflexad/physical/__init__.py
pyflexad/physical/electric_vehicle.py
pyflexad/physical/energy_storage.py
pyflexad/physical/pumped_hydro_energy_storage.py
pyflexad/physical/stationary_battery.py
pyflexad/physical/therm_load_cooling.py
pyflexad/physical/therm_load_heating.py
pyflexad/system/__init__.py
pyflexad/system/energy_prices.py
pyflexad/system/ev_data.py
pyflexad/system/household_data.py
pyflexad/utils/__init__.py
pyflexad/utils/algorithms.py
pyflexad/utils/benchmark.py
pyflexad/utils/file_utils.py
pyflexad/utils/network_graph.py
pyflexad/utils/progress_bar.py
pyflexad/utils/testing.py
pyflexad/utils/timer.py
pyflexad/utils/upr.py
pyflexad/virtual/__init__.py
pyflexad/virtual/aggregator.py
pyflexad/virtual/virtual_energy_storage.py
pyflexad-0.0.3.dist-info/METADATA
pyflexad-0.0.3.dist-info/WHEEL
pyflexad-0.0.3.dist-info/licenses/LICENSE
pyflexad-0.0.3.dist-info/RECORD
