Metadata-Version: 2.3
Name: pyflexad
Version: 0.0.3
Summary: Python Flexibility Aggregation and Disaggregation. 
Project-URL: Homepage, https://github.com/rce-fhv/pyflexad
Project-URL: Source, https://github.com/rce-fhv/pyflexad
Author-email: Kevin Kaspar <kevin.kaspar@fhv.at>, Emrah Öztürk <emrah.oeztuerk@fhv.at>
License: MIT License
Keywords: energy flexibility aggregation,energy storage systems,minkowski sum,optimization,virtual energy storage,virtual power plant
Classifier: Development Status :: 4 - Beta
Classifier: Intended Audience :: Science/Research
Classifier: License :: OSI Approved :: MIT License
Classifier: Programming Language :: Python :: 3 :: Only
Classifier: Programming Language :: Python :: 3.11
Classifier: Topic :: Scientific/Engineering
Requires-Python: ~=3.11
Requires-Dist: gurobipy~=10.0.3
Requires-Dist: highspy>=1.5.3
Requires-Dist: matplotlib~=3.8.4
Requires-Dist: networkx~=3.3
Requires-Dist: numba~=0.59.1
Requires-Dist: numpy~=1.26.4
Requires-Dist: pandas~=2.2.2
Requires-Dist: pycddlib~=2.1.7
Requires-Dist: pyomo~=6.7.1
Requires-Dist: scipy~=1.13.0
Requires-Dist: seaborn~=0.13.2
Requires-Dist: typing-extensions~=4.11.0
Provides-Extra: dev
Requires-Dist: jupyter; extra == 'dev'
